print_name_dmt25725-0.1.6.dist-info/DESCRIPTION.rst
print_name_dmt25725-0.1.6.dist-info/LICENSE.txt
print_name_dmt25725-0.1.6.dist-info/METADATA
print_name_dmt25725-0.1.6.dist-info/RECORD
print_name_dmt25725-0.1.6.dist-info/WHEEL
print_name_dmt25725-0.1.6.dist-info/metadata.json
print_name_dmt25725-0.1.6.dist-info/top_level.txt
testdist/__init__.py
testdist/printmyname.py
