Metadata-Version: 2.0
Name: print-name-dmt25725
Version: 0.1.6
Summary: example of name printing
Home-page: http://telegraph.co.uk
Author: David Thomson
Author-email: dmt257257@gmail.com
License: MIT
Keywords: sample setuptools development
Platform: UNKNOWN
Classifier: Intended Audience :: Education
Classifier: Topic :: Software Development
Classifier: Programming Language :: Python :: 3 :: Only
